LICENSE
MANIFEST.in
README.rst
setup.py
cmsplugin_question/__init__.py
cmsplugin_question/admin.py
cmsplugin_question/cms_plugins.py
cmsplugin_question/forms.py
cmsplugin_question/models.py
cmsplugin_question/settings.py
cmsplugin_question/utils.py
cmsplugin_question.egg-info/PKG-INFO
cmsplugin_question.egg-info/SOURCES.txt
cmsplugin_question.egg-info/dependency_links.txt
cmsplugin_question.egg-info/not-zip-safe
cmsplugin_question.egg-info/top_level.txt
cmsplugin_question/nospam/__init__.py
cmsplugin_question/nospam/fields.py
cmsplugin_question/nospam/forms.py
cmsplugin_question/nospam/utils.py
cmsplugin_question/nospam/widgets.py
cmsplugin_question/templates/cmsplugin_question/contact.html
cmsplugin_question/templates/cmsplugin_question/email.txt
cmsplugin_question/templates/cmsplugin_question/subject.txt
cmsplugin_question/templates/cmsplugin_question/admin/plugin_change_form.html