Metadata-Version: 1.1
Name: cmsplugin-question
Version: 1.0.5
Summary: Question form contact plugin
Home-page: http://github.com/vinitkumar/cmsplugin-question
Author: Vinit Kumar
Author-email: vinit.Kumar@changer.nl
License: UNKNOWN
Keywords: Question form django cms django-cms spam protection email
Platform: UNKNOWN
Classifier: Development Status :: 5 - Production/Stable
Classifier: Environment :: Web Environment
Classifier: Intended Audience :: Developers
Classifier: License :: OSI Approved :: BSD License
Classifier: Operating System :: OS Independent
Classifier: Programming Language :: Python
Classifier: Framework :: Django
